SimpleHTTPSAuthServer.py
SimpleHTTPSAuthServer-1.1.0.dist-info/LICENSE
SimpleHTTPSAuthServer-1.1.0.dist-info/METADATA
SimpleHTTPSAuthServer-1.1.0.dist-info/WHEEL
SimpleHTTPSAuthServer-1.1.0.dist-info/top_level.txt
SimpleHTTPSAuthServer-1.1.0.dist-info/RECORD
