Metadata-Version: 2.1
Name: SimpleHTTPSAuthServer
Version: 1.1.0
Summary: HTTPS server with Basic authentication and client certificate authentication.
Home-page: https://github.com/oza6ut0ne/SimpleHTTPSAuthServer
Author: Ryota Okimatsu
Author-email: oza6ut0ne@gmail.com
License: MIT
Platform: UNKNOWN
Classifier: License :: OSI Approved :: MIT License
Classifier: Programming Language :: Python :: 2
Classifier: Programming Language :: Python :: 2.7
Classifier: Programming Language :: Python :: 3
Classifier: Programming Language :: Python :: 3.4
Classifier: Programming Language :: Python :: 3.5
Classifier: Programming Language :: Python :: 3.6
Classifier: Programming Language :: Python :: 3.7
Classifier: Programming Language :: Python :: 3.8
